[
  {
    "py/object": "model.contact.Contact",
    "id": null,
    "firstname": "",
    "middlename": null,
    "lastname": "",
    "nickname": null,
    "title": null,
    "company": null,
    "address": "",
    "home": null,
    "mobile": null,
    "work": null,
    "all_phones": null,
    "all_emails": null,
    "fax": null,
    "email": null,
    "email2": null,
    "email3": null,
    "bday": null,
    "bmonth": null,
    "byear": null,
    "homepage": null,
    "aday": null,
    "amonth": null,
    "ayear": null,
    "new_group": null,
    "address2": null,
    "phone2": null,
    "notes": null
  },
  {
    "py/object": "model.contact.Contact",
    "id": null,
    "firstname": "firstnameF7PomT J",
    "middlename": null,
    "lastname": "lastname yZi",
    "nickname": null,
    "title": null,
    "company": null,
    "address": "addressABk",
    "home": null,
    "mobile": null,
    "work": null,
    "all_phones": null,
    "all_emails": null,
    "fax": null,
    "email": null,
    "email2": null,
    "email3": null,
    "bday": null,
    "bmonth": null,
    "byear": null,
    "homepage": null,
    "aday": null,
    "amonth": null,
    "ayear": null,
    "new_group": null,
    "address2": null,
    "phone2": null,
    "notes": null
  },
  {
    "py/object": "model.contact.Contact",
    "id": null,
    "firstname": "firstnamercpV",
    "middlename": null,
    "lastname": "lastname4W RMof0",
    "nickname": null,
    "title": null,
    "company": null,
    "address": "addressD2By9tSx4P",
    "home": null,
    "mobile": null,
    "work": null,
    "all_phones": null,
    "all_emails": null,
    "fax": null,
    "email": null,
    "email2": null,
    "email3": null,
    "bday": null,
    "bmonth": null,
    "byear": null,
    "homepage": null,
    "aday": null,
    "amonth": null,
    "ayear": null,
    "new_group": null,
    "address2": null,
    "phone2": null,
    "notes": null
  },
  {
    "py/object": "model.contact.Contact",
    "id": null,
    "firstname": "firstnamewn aM",
    "middlename": null,
    "lastname": "lastname hc",
    "nickname": null,
    "title": null,
    "company": null,
    "address": "addresswmky DeiMdnM",
    "home": null,
    "mobile": null,
    "work": null,
    "all_phones": null,
    "all_emails": null,
    "fax": null,
    "email": null,
    "email2": null,
    "email3": null,
    "bday": null,
    "bmonth": null,
    "byear": null,
    "homepage": null,
    "aday": null,
    "amonth": null,
    "ayear": null,
    "new_group": null,
    "address2": null,
    "phone2": null,
    "notes": null
  },
  {
    "py/object": "model.contact.Contact",
    "id": null,
    "firstname": "firstnamerShYavPJ",
    "middlename": null,
    "lastname": "lastname83sfFub",
    "nickname": null,
    "title": null,
    "company": null,
    "address": "addressB5y8yP7vm M JZ",
    "home": null,
    "mobile": null,
    "work": null,
    "all_phones": null,
    "all_emails": null,
    "fax": null,
    "email": null,
    "email2": null,
    "email3": null,
    "bday": null,
    "bmonth": null,
    "byear": null,
    "homepage": null,
    "aday": null,
    "amonth": null,
    "ayear": null,
    "new_group": null,
    "address2": null,
    "phone2": null,
    "notes": null
  },
  {
    "py/object": "model.contact.Contact",
    "id": null,
    "firstname": "firstnameEGOnQUgA",
    "middlename": null,
    "lastname": "lastname7 RbgKpmMag  IRl2",
    "nickname": null,
    "title": null,
    "company": null,
    "address": "address2d",
    "home": null,
    "mobile": null,
    "work": null,
    "all_phones": null,
    "all_emails": null,
    "fax": null,
    "email": null,
    "email2": null,
    "email3": null,
    "bday": null,
    "bmonth": null,
    "byear": null,
    "homepage": null,
    "aday": null,
    "amonth": null,
    "ayear": null,
    "new_group": null,
    "address2": null,
    "phone2": null,
    "notes": null
  }
]